Metadata-Version: 2.1
Name: SL-cities-extractor
Version: 0.1.0
Summary: Description of your library
Home-page: https://github.com/TharinduMadhusanka/SL_cities_extractor.git
License: UNKNOWN
Platform: UNKNOWN
